server_thread/__init__.py
server_thread/_version.py
server_thread/report.py
server_thread/server.py
tests/__init__.py
tests/conftest.py
tests/test_client.py
tests/test_manager.py
tests/test_report.py
tests/test_server.py
server_thread-0.2.0.dist-info/LICENSE
server_thread-0.2.0.dist-info/METADATA
server_thread-0.2.0.dist-info/WHEEL
server_thread-0.2.0.dist-info/top_level.txt
server_thread-0.2.0.dist-info/RECORD
