Metadata-Version: 2.1
Name: server-thread
Version: 0.2.0
Summary: Launch a WSGI or ASGI Application in a background thread with werkzeug or uvicorn.
Home-page: https://github.com/banesullivan/server-thread
Author: Bane Sullivan
Author-email: hello@banesullivan.com
License: UNKNOWN
Platform: UNKNOWN
Classifier: Development Status :: 3 - Alpha
Classifier: License :: OSI Approved :: MIT License
Classifier: Operating System :: OS Independent
Classifier: Programming Language :: Python :: 3
Classifier: Programming Language :: Python :: 3.8
Classifier: Programming Language :: Python
Requires-Python: >=3.7
